gimmebio.linked_reads-0.3.0-py3.6-nspkg.pth
gimmebio/linked_reads/__init__.py
gimmebio/linked_reads/cli.py
gimmebio/linked_reads/exceptions.py
gimmebio/linked_reads/readcloud_io.py
gimmebio/linked_reads/readclouds.py
gimmebio.linked_reads-0.3.0.dist-info/METADATA
gimmebio.linked_reads-0.3.0.dist-info/RECORD
gimmebio.linked_reads-0.3.0.dist-info/WHEEL
gimmebio.linked_reads-0.3.0.dist-info/namespace_packages.txt
gimmebio.linked_reads-0.3.0.dist-info/top_level.txt
