Metadata-Version: 2.1
Name: gimmebio.linked-reads
Version: 0.3.0
Summary: UNKNOWN
Home-page: UNKNOWN
Author: David Danko
Author-email: dcdanko@gmail.com
License: MIT license
Platform: UNKNOWN
Classifier: License :: OSI Approved :: MIT License
Classifier: Natural Language :: English
Classifier: Programming Language :: Python :: 3.6
Requires-Dist: gimmebio.seqs
